odoo/addons/sale_layout_category_hide_detail/README.rst
odoo/addons/sale_layout_category_hide_detail/__init__.py
odoo/addons/sale_layout_category_hide_detail/__manifest__.py
odoo/addons/sale_layout_category_hide_detail/i18n/es.po
odoo/addons/sale_layout_category_hide_detail/i18n/sale_layout_category_hide_detail.pot
odoo/addons/sale_layout_category_hide_detail/models/__init__.py
odoo/addons/sale_layout_category_hide_detail/models/account_move.py
odoo/addons/sale_layout_category_hide_detail/models/sale_order.py
odoo/addons/sale_layout_category_hide_detail/readme/CONTRIBUTORS.rst
odoo/addons/sale_layout_category_hide_detail/readme/DESCRIPTION.rst
odoo/addons/sale_layout_category_hide_detail/readme/ROADMAP.rst
odoo/addons/sale_layout_category_hide_detail/readme/USAGE.rst
odoo/addons/sale_layout_category_hide_detail/static/description/icon.png
odoo/addons/sale_layout_category_hide_detail/static/description/index.html
odoo/addons/sale_layout_category_hide_detail/static/description/readme-icons/eye-slash.png
odoo/addons/sale_layout_category_hide_detail/static/description/readme-icons/eye.png
odoo/addons/sale_layout_category_hide_detail/static/description/readme-icons/minus-circle.png
odoo/addons/sale_layout_category_hide_detail/static/description/readme-icons/plus-circle.png
odoo/addons/sale_layout_category_hide_detail/static/src/js/boolean_fa_icon_widget.js
odoo/addons/sale_layout_category_hide_detail/static/src/js/hide_details_translations.js
odoo/addons/sale_layout_category_hide_detail/static/src/js/sale_layout_category_hide_detail.js
odoo/addons/sale_layout_category_hide_detail/tests/__init__.py
odoo/addons/sale_layout_category_hide_detail/tests/test_sale_layout_category_hide_detail.py
odoo/addons/sale_layout_category_hide_detail/views/account_move_view.xml
odoo/addons/sale_layout_category_hide_detail/views/assets.xml
odoo/addons/sale_layout_category_hide_detail/views/invoice_report_templates.xml
odoo13_addon_sale_layout_category_hide_detail-13.0.1.1.0.dist-info/METADATA
odoo13_addon_sale_layout_category_hide_detail-13.0.1.1.0.dist-info/WHEEL
odoo13_addon_sale_layout_category_hide_detail-13.0.1.1.0.dist-info/top_level.txt
odoo13_addon_sale_layout_category_hide_detail-13.0.1.1.0.dist-info/RECORD
