Metadata-Version: 2.1
Name: odoo13-addon-sale-layout-category-hide-detail
Version: 13.0.1.1.0
Summary: Hide details for sections in sale orders and invoices for reports and customer portal
Home-page: https://github.com/OCA/sale-reporting
Author: Tecnativa, Odoo Community Association (OCA)
Author-email: support@odoo-community.org
License: AGPL-3
Platform: UNKNOWN
Classifier: Programming Language :: Python
Classifier: Framework :: Odoo
Classifier: License :: OSI Approved :: GNU Affero General Public License v3
Requires-Python: >=3.5
Requires-Dist: odoo (<13.1dev,>=13.0a)
